libscreen/__init__.py
libscreen-69.0.8.dist-info/METADATA
libscreen-69.0.8.dist-info/WHEEL
libscreen-69.0.8.dist-info/top_level.txt
libscreen-69.0.8.dist-info/RECORD
