Metadata-Version: 2.1
Name: libscreen
Version: 69.0.8
Summary: long description
Home-page: https://github.com/your/github/project
Author: Your name
Author-email: your@email.com
License: UNKNOWN
Platform: UNKNOWN
Classifier: Programming Language :: Python :: 3
Classifier: License :: OSI Approved :: MIT License
Classifier: Operating System :: OS Independent
